MANIFEST.in
setup.py
picalo/Benfords.py
picalo/Boolean.py
picalo/CHANGELOG.txt
picalo/Calendar.py
picalo/Column.py
picalo/Crosstable.py
picalo/Currency.py
picalo/Database.py
picalo/Error.py
picalo/Expression.py
picalo/Financial.py
picalo/Grouping.py
picalo/LICENSE.txt
picalo/Number.py
picalo/Project.py
picalo/README.txt
picalo/Record.py
picalo/Simple.py
picalo/Table.py
picalo/TableArray.py
picalo/TableList.py
picalo/Trending.py
picalo/VERSION.txt
picalo/__init__.py
picalo.egg-info/PKG-INFO
picalo.egg-info/SOURCES.txt
picalo.egg-info/dependency_links.txt
picalo.egg-info/requires.txt
picalo.egg-info/top_level.txt
picalo/lib/GUID.py
picalo/lib/__init__.py
picalo/lib/delimitedtext.py
picalo/lib/progressbar.py
picalo/lib/pstat.py
picalo/lib/stats.py
picalo/lib/pyExcelerator/BIFFRecords.py
picalo/lib/pyExcelerator/Bitmap.py
picalo/lib/pyExcelerator/Cell.py
picalo/lib/pyExcelerator/Column.py
picalo/lib/pyExcelerator/CompoundDoc.py
picalo/lib/pyExcelerator/Deco.py
picalo/lib/pyExcelerator/ExcelFormula.py
picalo/lib/pyExcelerator/ExcelFormulaLexer.py
picalo/lib/pyExcelerator/ExcelFormulaParser.py
picalo/lib/pyExcelerator/ExcelMagic.py
picalo/lib/pyExcelerator/Formatting.py
picalo/lib/pyExcelerator/ImportXLS.py
picalo/lib/pyExcelerator/Row.py
picalo/lib/pyExcelerator/Style.py
picalo/lib/pyExcelerator/UnicodeUtils.py
picalo/lib/pyExcelerator/Utils.py
picalo/lib/pyExcelerator/Workbook.py
picalo/lib/pyExcelerator/Worksheet.py
picalo/lib/pyExcelerator/__init__.py
picalo/lib/pyExcelerator/antlr.py