Metadata-Version: 1.0
Name: picalo
Version: 4.93
Summary: A data analysis/structure library with tables, type-aware columns, records, and cells.
Home-page: http://www.picalo.org/
Author: Conan C. Albrecht
Author-email: conan@warp.byu.edu
License: Picalo itself is released under the GNU General Public License (GPL).
